Workbook
Name Aporte: 'Simulação de Investimento'!$J$18
Name Qtd_Anos: 'Simulação de Investimento'!$J$19
Name Rendimento_Carteira: 'Simulação de Investimento'!$J$14
Name Salario: 'Simulação de Investimento'!$J$13
Name Sugestao_investimento: 'Simulação de Investimento'!$J$15
Name Taxa_Mensal: 'Simulação de Investimento'!$J$20

Sheet Simulação de Investimento
B12: CONFIGURAÇÕES
B13: Salário | J13: 5000
B14: Rendimento Carteira | J14: 0.0089
B15: Sugestões de Investimento | J15: =Salario*0.3 -> 1500
B17: INVESTIMENTO MENSAL
B18: Quanto investir por mês? | J18: 300
B19: Por quantos anos? | J19: 5
B20: Taxa de rendimento mensal? | J20: 0.0108
B21: Patrimônio acumulado? | J21: =FV(Taxa_Mensal,Qtd_Anos*12,-1*Aporte) -> 25141.206
B22: Dividendos mensais? | J22: =J21*1% -> 251.41206
B24: CENÁRIOS | J24: Dividendos
A25: 2 | B25: Quanto em 2 anos? | I25: =FV(Taxa_Mensal,A25*12,Aporte*-1) -> 8169.2591 | J25: =I25*Rendimento_Carteira -> 72.706406
A26: 5 | B26: Quanto em 5 anos? | I26: =FV(Taxa_Mensal,A26*12,Aporte*-1) -> 25141.206 | J26: =I26*Rendimento_Carteira -> 223.75673
A27: 10 | B27: Quanto em 10 anos? | I27: =FV(Taxa_Mensal,A27*12,Aporte*-1) -> 73037.3 | J27: =I27*Rendimento_Carteira -> 650.03197
A28: 20 | B28: Quanto em 20 anos? | I28: =FV(Taxa_Mensal,A28*12,Aporte*-1) -> 338114.7 | J28: =I28*Rendimento_Carteira -> 3009.2208
A29: 30 | B29: Quanto em 30 anos? | I29: =FV(Taxa_Mensal,A29*12,Aporte*-1) -> 1300171.4 | J29: =I29*Rendimento_Carteira -> 11571.526
B31: PERFIL | J31: Moderado
B32: Valor a ser investido por mês | J32: =Aporte -> 300
A34: Tipos de FI | B34: Tipos de FI | I34: Percentual Sugerido | J34: Valores
A35: Papel | B35: Papel | I35: {=_xlfn.XLOOKUP(1,(B35='Dados do Perfil'!$C$3:$C$20)*('Simulação de Investimento'!$J$31='Dados do Perfil'!$B$3:$B$20),'Dados do Perfil'!$D$3:$D$20)} -> 0.32 | J35: =I35*$J$32 -> 96
A36: Tijolo | B36: Tijolo | I36: {=_xlfn.XLOOKUP(1,(B36='Dados do Perfil'!$C$3:$C$20)*('Simulação de Investimento'!$J$31='Dados do Perfil'!$B$3:$B$20),'Dados do Perfil'!$D$3:$D$20)} -> 0.35 | J36: =I36*$J$32 -> 105
A37: Híbridos | B37: Híbridos | I37: {=_xlfn.XLOOKUP(1,(B37='Dados do Perfil'!$C$3:$C$20)*('Simulação de Investimento'!$J$31='Dados do Perfil'!$B$3:$B$20),'Dados do Perfil'!$D$3:$D$20)} -> 0.08 | J37: =I37*$J$32 -> 24
A38: FOFs | B38: FOFs | I38: {=_xlfn.XLOOKUP(1,(B38='Dados do Perfil'!$C$3:$C$20)*('Simulação de Investimento'!$J$31='Dados do Perfil'!$B$3:$B$20),'Dados do Perfil'!$D$3:$D$20)} -> 0.05 | J38: =I38*$J$32 -> 15
A39: Desenvolvimento | B39: Desenvolvimento | I39: {=_xlfn.XLOOKUP(1,(B39='Dados do Perfil'!$C$3:$C$20)*('Simulação de Investimento'!$J$31='Dados do Perfil'!$B$3:$B$20),'Dados do Perfil'!$D$3:$D$20)} -> 0.1 | J39: =I39*$J$32 -> 30
A40: Hotelaria | B40: Hotelaria | I40: {=_xlfn.XLOOKUP(1,(B40='Dados do Perfil'!$C$3:$C$20)*('Simulação de Investimento'!$J$31='Dados do Perfil'!$B$3:$B$20),'Dados do Perfil'!$D$3:$D$20)} -> 0.1 | J40: =I40*$J$32 -> 30
J41: =SUM(J35:J40) -> 300

Sheet Dados do Perfil
B2: Perfil | C2: Tipos de FI | D2: %
B3: Conservador | C3: Papel | D3: 0.3
B4: Conservador | C4: Tijolo | D4: 0.5
B5: Conservador | C5: Híbridos | D5: 0.1
B6: Conservador | C6: FOFs | D6: 0.1
B7: Conservador | C7: Desenvolvimento | D7: 0
B8: Conservador | C8: Hotelaria | D8: 0
B9: Moderado | C9: Papel | D9: 0.32
B10: Moderado | C10: Tijolo | D10: 0.35
B11: Moderado | C11: Híbridos | D11: 0.08
B12: Moderado | C12: FOFs | D12: 0.05
B13: Moderado | C13: Desenvolvimento | D13: 0.1
B14: Moderado | C14: Hotelaria | D14: 0.1
... B20: Agressivo | C20: Hotelaria | D20: 0.1
